langchain_upstage/__init__.py
langchain_upstage/chat_models.py
langchain_upstage/document_parse.py
langchain_upstage/document_parse_parsers.py
langchain_upstage/embeddings.py
langchain_upstage/py.typed
langchain_upstage/tools/prebuilt_information_extraction.py
langchain_upstage/tools/universal_information_extraction.py
langchain_upstage/utils/__init__.py
langchain_upstage/utils/constants.py
langchain_upstage/utils/file_utils.py
langchain_upstage/utils/response_generator.py
langchain_upstage/utils/value_retriever.py
langchain_upstage-0.7.6.dist-info/LICENSE
langchain_upstage-0.7.6.dist-info/METADATA
langchain_upstage-0.7.6.dist-info/WHEEL
langchain_upstage-0.7.6.dist-info/RECORD
