Metadata-Version: 2.1
Name: langchain-upstage
Version: 0.7.6
Summary: An integration package connecting Upstage and LangChain
Home-page: https://github.com/langchain-ai/langchain-upstage
License: MIT
Requires-Python: >=3.10,<4.0
Classifier: License :: OSI Approved :: MIT License
Classifier: Programming Language :: Python :: 3
Classifier: Programming Language :: Python :: 3.10
Classifier: Programming Language :: Python :: 3.11
Classifier: Programming Language :: Python :: 3.12
Requires-Dist: langchain-core (>=1.0.3,<2.0.0)
Requires-Dist: langchain-openai (>=1.0.2,<2.0.0)
Requires-Dist: pypdf (>=4.2.0,<7.0.0)
Requires-Dist: requests (>=2.31.0,<3.0.0)
Requires-Dist: tokenizers (>=0.20.0,<0.21.0)
Project-URL: Repository, https://github.com/langchain-ai/langchain-upstage
Project-URL: Source Code, https://github.com/langchain-ai/langchain-upstage/tree/main/libs/upstage
